chatie_grpc/__init__.py
chatie_grpc/wechaty/__init__.py
chatie_grpc-0.18.12.dist-info/METADATA
chatie_grpc-0.18.12.dist-info/WHEEL
chatie_grpc-0.18.12.dist-info/top_level.txt
chatie_grpc-0.18.12.dist-info/RECORD
