Metadata-Version: 2.1
Name: chatie-grpc
Version: 0.18.12
Summary: gRPC for Chatie
Home-page: https://github.com/chatie/grpc
Author: Huan LI (李卓桓)
Author-email: zixia@zixia.net
License: Apache-2.0
Platform: UNKNOWN
Classifier: Programming Language :: Python :: 3.7
Classifier: License :: OSI Approved :: Apache Software License
Classifier: Operating System :: OS Independent
Requires-Dist: betterproto
Requires-Dist: grpclib
